README.rst
setup.py
influxdb_pytest_plugin/__init__.py
influxdb_pytest_plugin/influxdb_components.py
influxdb_pytest_plugin/influxdb_pytest_plugin.py
influxdb_pytest_plugin/suite_result_dto.py
influxdb_pytest_plugin/test_result_dto.py
influxdb_pytest_plugin.egg-info/PKG-INFO
influxdb_pytest_plugin.egg-info/SOURCES.txt
influxdb_pytest_plugin.egg-info/dependency_links.txt
influxdb_pytest_plugin.egg-info/entry_points.txt
influxdb_pytest_plugin.egg-info/requires.txt
influxdb_pytest_plugin.egg-info/top_level.txt