Metadata-Version: 1.1
Name: influxdb-pytest-plugin
Version: 0.2.57
Summary: Plugin for influxdb and pytest integration.
Home-page: UNKNOWN
Author: Strike Team
Author-email: elenaramyan@workfront.com
License: UNKNOWN
Platform: UNKNOWN
Classifier: Programming Language :: Python :: 3
